{"summaries":[{"symbol":{"__symbol":0,"members":[]},"metadata":{"__symbol":1,"members":[]}},{"symbol":{"__symbol":2,"members":[]},"metadata":{"__symbol":3,"members":[]}},{"symbol":{"__symbol":4,"members":[]},"metadata":{"__symbol":5,"members":[]}},{"symbol":{"__symbol":6,"members":[]},"metadata":{"__symbol":7,"members":[]}}],"symbols":[{"__symbol":0,"name":"CKEditorModule","filePath":"/home/andrey/CODE/ng2-ckeditor/src/index.d.ts"},{"__symbol":1,"name":"CKEditorModule","filePath":"/home/andrey/CODE/ng2-ckeditor/src/ckeditor.module.d.ts"},{"__symbol":2,"name":"CKEditorComponent","filePath":"/home/andrey/CODE/ng2-ckeditor/src/index.d.ts"},{"__symbol":3,"name":"CKEditorComponent","filePath":"/home/andrey/CODE/ng2-ckeditor/src/ckeditor.component.d.ts"},{"__symbol":4,"name":"CKButtonDirective","filePath":"/home/andrey/CODE/ng2-ckeditor/src/index.d.ts"},{"__symbol":5,"name":"CKButtonDirective","filePath":"/home/andrey/CODE/ng2-ckeditor/src/ckbutton.directive.d.ts"},{"__symbol":6,"name":"CKGroupDirective","filePath":"/home/andrey/CODE/ng2-ckeditor/src/index.d.ts"},{"__symbol":7,"name":"CKGroupDirective","filePath":"/home/andrey/CODE/ng2-ckeditor/src/ckgroup.directive.d.ts"}]}